snitch/__init__.py
snitch/admin.py
snitch/apps.py
snitch/backends.py
snitch/constants.py
snitch/cooldowns.py
snitch/decorators.py
snitch/emails.py
snitch/exceptions.py
snitch/handlers.py
snitch/helpers.py
snitch/locale/es_ES/LC_MESSAGES/django.po
snitch/managers.py
snitch/migrations/0001_initial.py
snitch/migrations/0002_alter_eventtype_verb.py
snitch/migrations/0003_alter_eventtype_verb.py
snitch/migrations/0004_alter_event_id_alter_eventtype_id_and_more.py
snitch/migrations/0005_notification_receiver_content_type_and_more.py
snitch/migrations/0006_auto_20230220_0641.py
snitch/migrations/0007_remove_notification_user.py
snitch/migrations/__init__.py
snitch/models.py
snitch/schedules/__init__.py
snitch/schedules/admin.py
snitch/schedules/apps.py
snitch/schedules/migrations/0001_initial.py
snitch/schedules/migrations/0002_auto_20191118_0940.py
snitch/schedules/migrations/0003_alter_schedule_verb.py
snitch/schedules/migrations/0004_alter_schedule_id.py
snitch/schedules/migrations/__init__.py
snitch/schedules/models.py
snitch/schedules/tasks.py
snitch/settings.py
snitch/tasks.py
django_snitch-3.2.0.dist-info/LICENSE
django_snitch-3.2.0.dist-info/METADATA
django_snitch-3.2.0.dist-info/WHEEL
django_snitch-3.2.0.dist-info/RECORD
