Metadata-Version: 2.1
Name: django-snitch
Version: 3.2.0
Summary: Django app made to integrate generic events that create notifications that can be sent to users using several backends.
Home-page: https://github.com/marcosgabarda/django-snitch
License: MIT
Author: Marcos Gabarda
Author-email: hey@marcosgabarda.com
Requires-Python: >=3.10,<4.0
Classifier: Environment :: Web Environment
Classifier: Framework :: Django
Classifier: License :: OSI Approved :: MIT License
Classifier: Programming Language :: Python :: 3
Classifier: Programming Language :: Python :: 3.10
Classifier: Programming Language :: Python :: 3.11
Requires-Dist: bleach (>=4.1.0)
Requires-Dist: celery (>=5.0.0)
Requires-Dist: django (>=3.0.0)
Requires-Dist: django-celery-beat (>=2.4.0)
Requires-Dist: django-model-utils (>=4.1.1)
Requires-Dist: django-push-notifications (>=2.0.0)
Requires-Dist: single-source (>=0.3.0)
